phelel/__init__.py
phelel/api_phelel.py
phelel/file_IO.py
phelel/version.py
phelel/base/Dij_qij.py
phelel/base/__init__.py
phelel/base/local_potential.py
phelel/cui/__init__.py
phelel/cui/create_supercells.py
phelel/cui/load.py
phelel/cui/phelel_argparse.py
phelel/cui/phelel_script.py
phelel/cui/settings.py
phelel/interface/__init__.py
phelel/interface/phelel_yaml.py
phelel/interface/vasp/__init__.py
phelel/interface/vasp/derivatives.py
phelel/interface/vasp/file_IO.py
phelel/interface/vasp/procar.py
phelel/interface/vasp/show_data.py
phelel/scripts/phelel.py
phelel/scripts/phelel_load.py
phelel/utils/__init__.py
phelel/utils/data.py
phelel/utils/eliashberg_tool.py
phelel/utils/lattice_points.py
phelel/utils/spherical_harmonics.py
phelel/utils/spinor.py
phelel/velph/__init__.py
phelel/velph/cli/__init__.py
phelel/velph/cli/utils.py
phelel/velph/cli/el_bands/__init__.py
phelel/velph/cli/el_bands/generate.py
phelel/velph/cli/el_bands/plot.py
phelel/velph/cli/generate/__init__.py
phelel/velph/cli/hints/__init__.py
phelel/velph/cli/init/__init__.py
phelel/velph/cli/init/init.py
phelel/velph/cli/nac/__init__.py
phelel/velph/cli/nac/generate.py
phelel/velph/cli/ph_bands/__init__.py
phelel/velph/cli/ph_bands/generate.py
phelel/velph/cli/ph_bands/plot.py
phelel/velph/cli/phelel/__init__.py
phelel/velph/cli/phelel/differentiate.py
phelel/velph/cli/phelel/generate.py
phelel/velph/cli/phelel/init.py
phelel/velph/cli/phelel/phonopy.py
phelel/velph/cli/phono3py/__init__.py
phelel/velph/cli/phono3py/generate.py
phelel/velph/cli/phono3py/init.py
phelel/velph/cli/relax/__init__.py
phelel/velph/cli/relax/generate.py
phelel/velph/cli/selfenergy/__init__.py
phelel/velph/cli/selfenergy/generate.py
phelel/velph/cli/transport/__init__.py
phelel/velph/cli/transport/generate.py
phelel/velph/cli/transport/plot/__init__.py
phelel/velph/cli/transport/plot/plot_eigenvalues.py
phelel/velph/cli/transport/plot/plot_selfenergy.py
phelel/velph/cli/transport/plot/plot_transport.py
phelel-0.6.1.dist-info/LICENSE
phelel-0.6.1.dist-info/METADATA
phelel-0.6.1.dist-info/WHEEL
phelel-0.6.1.dist-info/entry_points.txt
phelel-0.6.1.dist-info/top_level.txt
phelel-0.6.1.dist-info/RECORD
