Metadata-Version: 2.1
Name: phelel
Version: 0.6.1
Summary: Electron-phonon code.
Author-email: Atsushi Togo <atztogo@gmail.com>
License: BSD 3-Clause License
Requires-Python: >=3.9
License-File: LICENSE
Requires-Dist: phono3py
Requires-Dist: finufft
Requires-Dist: click
Requires-Dist: tomli
Requires-Dist: tomli-w
